sqlalchemy_oso/__init__.py
sqlalchemy_oso/auth.py
sqlalchemy_oso/compat.py
sqlalchemy_oso/flask.py
sqlalchemy_oso/oso.py
sqlalchemy_oso/partial.py
sqlalchemy_oso/preprocess.py
sqlalchemy_oso/roles.py
sqlalchemy_oso/roles_old.py
sqlalchemy_oso/session.py
sqlalchemy_oso_preview-0.8.0.dist-info/METADATA
sqlalchemy_oso_preview-0.8.0.dist-info/WHEEL
sqlalchemy_oso_preview-0.8.0.dist-info/entry_points.txt
sqlalchemy_oso_preview-0.8.0.dist-info/top_level.txt
sqlalchemy_oso_preview-0.8.0.dist-info/RECORD
