Metadata-Version: 2.1
Name: sqlalchemy-oso-preview
Version: 0.8.0
Summary: oso sqlalchemy integration
Home-page: UNKNOWN
Author: Oso Security, Inc.
Author-email: support@osohq.com
License: UNKNOWN
Project-URL: Source, https://github.com/osohq/oso/tree/main/languages/python/sqlalchemy-oso
Platform: UNKNOWN
Classifier: Development Status :: 4 - Beta
Classifier: Programming Language :: Python :: 3.6
Classifier: License :: OSI Approved :: Apache Software License
Requires-Python: >=3.6
Requires-Dist: oso (~=0.12.4)
Requires-Dist: SQLAlchemy (<1.5,>=1.3.17)
Requires-Dist: packaging (~=20.9)
Requires-Dist: dataclasses ; python_version < "3.7"
Provides-Extra: flask
Requires-Dist: flask ; extra == 'flask'
Requires-Dist: flask-sqlalchemy ; extra == 'flask'
